discreetly/__init__.py
discreetly/cli.py
discreetly/session.py
discreetly/backends/__init__.py
discreetly/backends/aws/__init__.py
discreetly/backends/gcp/__init__.py
discreetly-0.2.0.dist-info/LICENSE.txt
discreetly-0.2.0.dist-info/METADATA
discreetly-0.2.0.dist-info/WHEEL
discreetly-0.2.0.dist-info/entry_points.txt
discreetly-0.2.0.dist-info/top_level.txt
discreetly-0.2.0.dist-info/RECORD
