Metadata-Version: 2.1
Name: discreetly
Version: 0.2.0
Summary: A secrets manager for AWS and GCP
Home-page: https://github.com/tra-sg/discreetly
Author: TRA
Author-email: no-reply@tra.sg
License: UNKNOWN
Keywords: discreetly secrets aws gcp kms keys passwords
Platform: UNKNOWN
Classifier: Development Status :: 3 - Alpha
Classifier: Intended Audience :: Developers
Classifier: Topic :: Software Development :: Build Tools
Classifier: License :: OSI Approved :: GNU Lesser General Public License v2 (LGPLv2)
Classifier: Programming Language :: Python :: 2
Classifier: Programming Language :: Python :: 2.7
Classifier: Programming Language :: Python :: 3
Classifier: Programming Language :: Python :: 3.3
Classifier: Programming Language :: Python :: 3.4
Classifier: Programming Language :: Python :: 3.5
Classifier: Programming Language :: Python :: 3.6
Classifier: Programming Language :: Python :: 3.7
Classifier: Programming Language :: Python :: 3.8
Requires-Python: >=2.7, !=3.0.*, !=3.1.*, !=3.2.*, <4
Requires-Dist: future
Provides-Extra: aws
Requires-Dist: boto3 ; extra == 'aws'
Provides-Extra: cli
Requires-Dist: click ; extra == 'cli'
Requires-Dist: boto3 ; extra == 'cli'
Requires-Dist: google-cloud-kms (<3.0.0,>=2.0.0) ; extra == 'cli'
Requires-Dist: google-cloud-datastore ; extra == 'cli'
Provides-Extra: gcp
Requires-Dist: google-cloud-kms (<3.0.0,>=2.0.0) ; extra == 'gcp'
Requires-Dist: google-cloud-datastore ; extra == 'gcp'
Provides-Extra: test
Requires-Dist: tox ; extra == 'test'
Requires-Dist: pytest ; extra == 'test'
Requires-Dist: pytest-cov ; extra == 'test'
Requires-Dist: mock ; extra == 'test'
Requires-Dist: flake8 ; extra == 'test'
Requires-Dist: moto ; extra == 'test'
Requires-Dist: black ; extra == 'test'
